reacnetgenerator-1.6.15.dist-info/RECORD
reacnetgenerator-1.6.15.dist-info/entry_points.txt
reacnetgenerator-1.6.15.dist-info/METADATA
reacnetgenerator-1.6.15.dist-info/WHEEL
reacnetgenerator-1.6.15.dist-info/licenses/LICENSE
reacnetgenerator/tools.py
reacnetgenerator/utils.py
reacnetgenerator/_path.py
reacnetgenerator/_hmmfilter.py
reacnetgenerator/reacnetgen.py
reacnetgenerator/utils_np.pyx
reacnetgenerator/dps.pyx
reacnetgenerator/__init__.py
reacnetgenerator/dps.abi3.so
reacnetgenerator/gui.py
reacnetgenerator/_version.py
reacnetgenerator/_reachtml.py
reacnetgenerator/_detect.py
reacnetgenerator/__main__.py
reacnetgenerator/_draw.py
reacnetgenerator/c_stack.cpp
reacnetgenerator/_reaction.py
reacnetgenerator/_download.py
reacnetgenerator/_logging.py
reacnetgenerator/c_stack.h
reacnetgenerator/commandline.py
reacnetgenerator/py.typed
reacnetgenerator/_matrix.py
reacnetgenerator/static/img-title.png
reacnetgenerator/static/webpack/bundle.html
