Metadata-Version: 2.1
Name: reacnetgenerator
Version: 1.6.15
Summary: ReacNetGenerator: An automatic reaction network generator for reactive molecular dynamics simulation.
Keywords: reaction network
Home-page: https://github.com/deepmodeling/reacnetgenerator
Author-Email: Jinzhe Zeng <jinzhe.zeng@rutgers.edu>
License:                    GNU LESSER GENERAL PUBLIC LICENSE
Classifier: Natural Language :: English
Classifier: Operating System :: POSIX :: Linux
Classifier: Operating System :: Microsoft :: Windows
Classifier: Programming Language :: Python :: 3.7
Classifier: Programming Language :: Python :: 3.8
Classifier: Programming Language :: Python :: 3.9
Classifier: Programming Language :: Python :: 3.10
Classifier: Programming Language :: Python :: 3.11
Classifier: Programming Language :: Python :: 3.12
Classifier: Programming Language :: JavaScript
Classifier: Programming Language :: C
Classifier: Programming Language :: Cython
Classifier: Topic :: Scientific/Engineering :: Chemistry
Classifier: Topic :: Scientific/Engineering :: Visualization
Classifier: Topic :: Software Development :: Libraries :: Python Modules
Classifier: Topic :: Software Development :: Version Control :: Git
Classifier: Development Status :: 6 - Mature
Classifier: Environment :: Console
Classifier: Intended Audience :: Science/Research
Classifier: License :: OSI Approved :: GNU Lesser General Public License v3 (LGPLv3)
Project-URL: Homepage, https://github.com/deepmodeling/reacnetgenerator
Project-URL: Documentation, https://docs.deepmodeling.com/projects/reacnetgenerator/
Project-URL: Repository, https://github.com/deepmodeling/reacnetgenerator
Requires-Python: >=3.7
Requires-Dist: numpy
Requires-Dist: networkx
Requires-Dist: matplotlib
Requires-Dist: hmmlearn>=0.2.1
Requires-Dist: ase
Requires-Dist: scour
Requires-Dist: tqdm>=4.9.0
Requires-Dist: coloredlogs
Requires-Dist: pandas
Requires-Dist: lz4
Requires-Dist: requests
Requires-Dist: openbabel-wheel
Requires-Dist: rdkit
Requires-Dist: packaging
Requires-Dist: pytest-sugar; extra == "test"
Requires-Dist: pytest-cov<4; extra == "test"
Requires-Dist: cython; extra == "test"
Requires-Dist: pytest-xvfb; extra == "test"
Requires-Dist: pytest-console-scripts; extra == "test"
Requires-Dist: pytest-mock; extra == "test"
Requires-Dist: pytest-codspeed; extra == "test"
Requires-Dist: sphinx; extra == "docs"
Requires-Dist: sphinx-book-theme; extra == "docs"
Requires-Dist: numpydoc; extra == "docs"
Requires-Dist: sphinx-argparse<0.5.0; extra == "docs"
Requires-Dist: myst-nb>=1.0.0rc0; extra == "docs"
Requires-Dist: sphinx-favicon>=1.0; extra == "docs"
Requires-Dist: nodejs-wheel~=20.9; extra == "docs"
Requires-Dist: pyyaml; extra == "docs"
Requires-Dist: deepmodeling_sphinx>=0.1.3; extra == "docs"
Requires-Dist: pygments-lammps; extra == "docs"
Requires-Dist: sphinxcontrib-bibtex>=2.6.0; extra == "docs"
Requires-Dist: setuptools; extra == "docs"
Requires-Dist: sphinx-design; extra == "docs"
Provides-Extra: test
Provides-Extra: docs
